cyberstorm/__init__.py
cyberstorm/attestor/__init__.py
cyberstorm/attestor/v1/__init__.py
cyberstorm/attestor/v1/messages_pb2.py
cyberstorm/attestor/v1/messages_pb2_grpc.py
cyberstorm/attestor/v1/services_pb2.py
cyberstorm/attestor/v1/services_pb2_grpc.py
cyberstorm/buf/__init__.py
cyberstorm/buf/validate/__init__.py
cyberstorm/buf/validate/validate_pb2.py
cyberstorm/buf/validate/validate_pb2_grpc.py
cyberstorm/crypto/__init__.py
cyberstorm/crypto/v1/__init__.py
cyberstorm/crypto/v1/crypto_pb2.py
cyberstorm/crypto/v1/crypto_pb2_grpc.py
cyberstorm_schemas-1.0.5.dist-info/licenses/LICENSE
cyberstorm_schemas-1.0.5.dist-info/METADATA
cyberstorm_schemas-1.0.5.dist-info/WHEEL
cyberstorm_schemas-1.0.5.dist-info/__init__.py
cyberstorm_schemas-1.0.5.dist-info/top_level.txt
cyberstorm_schemas-1.0.5.dist-info/RECORD
